<?xml version="1.0" encoding="utf-8" ?>
<Defs>
    <ThinkTreeDef>
        <defName>RPGILoadoutCore</defName>
        <insertTag>Humanlike_PostDuty</insertTag>
        <insertPriority>100</insertPriority>
        <thinkRoot Class="AwesomeInventory.Loadout.ThinkNode_AwesomeInventory_Core">
            <subNodes>
                <li Class="AwesomeInventory.Loadout.JobGiver_AwesomeInventory_FindApparels"></li>
                <li Class="AwesomeInventory.Jobs.JobGiver_RPGI_FindItems"></li>
                <li Class="AwesomeInventory.Jobs.JobGiver_RPGI_FindWeapon"></li>
                <li Class="AwesomeInventory.Jobs.JobGiver_RPGI_OpportunisticHaul"></li>
            </subNodes>
        </thinkRoot>
    </ThinkTreeDef>
</Defs>
